card_framework/__init__.py
card_framework/__init_test.py
card_framework/v2/__init__.py
card_framework/v2/action_response.py
card_framework/v2/action_response_test.py
card_framework/v2/action_status.py
card_framework/v2/annotation.py
card_framework/v2/annotation_test.py
card_framework/v2/attachment.py
card_framework/v2/card.py
card_framework/v2/card_action.py
card_framework/v2/card_fixed_footer.py
card_framework/v2/card_header.py
card_framework/v2/card_header_test.py
card_framework/v2/card_test.py
card_framework/v2/dialog_action.py
card_framework/v2/emoji.py
card_framework/v2/enums.py
card_framework/v2/message.py
card_framework/v2/message_test.py
card_framework/v2/section.py
card_framework/v2/section_test.py
card_framework/v2/space.py
card_framework/v2/user.py
card_framework/v2/widget.py
card_framework/v2/widget_test.py
card_framework/v2/widgets/__init__.py
card_framework/v2/widgets/action.py
card_framework/v2/widgets/button.py
card_framework/v2/widgets/button_list.py
card_framework/v2/widgets/button_test.py
card_framework/v2/widgets/chip_list.py
card_framework/v2/widgets/chip_list_test.py
card_framework/v2/widgets/color.py
card_framework/v2/widgets/color_test.py
card_framework/v2/widgets/columns.py
card_framework/v2/widgets/columns_test.py
card_framework/v2/widgets/date_time_picker.py
card_framework/v2/widgets/date_time_picker_test.py
card_framework/v2/widgets/decorated_text.py
card_framework/v2/widgets/divider.py
card_framework/v2/widgets/divider_test.py
card_framework/v2/widgets/grid.py
card_framework/v2/widgets/icon.py
card_framework/v2/widgets/icon_test.py
card_framework/v2/widgets/image.py
card_framework/v2/widgets/image_test.py
card_framework/v2/widgets/on_click.py
card_framework/v2/widgets/on_click_test.py
card_framework/v2/widgets/open_link.py
card_framework/v2/widgets/overflow_menu.py
card_framework/v2/widgets/selection_input.py
card_framework/v2/widgets/selection_input_test.py
card_framework/v2/widgets/selection_item.py
python_card_framework-2.4.0.dist-info/licenses/LICENSE
python_card_framework-2.4.0.dist-info/METADATA
python_card_framework-2.4.0.dist-info/WHEEL
python_card_framework-2.4.0.dist-info/top_level.txt
python_card_framework-2.4.0.dist-info/RECORD
