Metadata-Version: 2.4
Name: python-card-framework
Version: 2.4.0
Summary: API for rendering Chat App Card json.
Author-email: David Harcombe <david.harcombe@gmail.com>
License: Apache 2.0
Project-URL: Homepage, https://github.com/google/python-card-framework
Project-URL: Bug Tracker, https://github.com/google/python-card-framework/issues
Classifier: Programming Language :: Python :: 3
Classifier: Operating System :: OS Independent
Requires-Python: >=3.10
License-File: LICENSE
Requires-Dist: dataclasses-json>=0.5.2
Requires-Dist: stringcase>=1.2.0
Dynamic: license-file
